{"title":"links","type":"friends","uid":"9f87b2c4067d21986f9f47834c8a9256","text":" 你可以在下方评论区留言你的网站 ","date":"2024-01-13T06:05:47.000Z","updated":"2024-04-01T15:22:25.696Z","comments":true,"path":"api/pages/links/index.json","covers":null,"excerpt":"","content":"<div style=\"margin: 0 auto; margin-left: 75px; width: auto;\">\n<div>你可以在下方评论区留言你的网站</div>\n</div>","count_time":{"symbolsCount":17,"symbolsTime":"1 mins."},"toc":"","categoryMode":true,"avatarWall":[[{"nick":"GitHub","link":"https://github.com","description":"GitHub is the world's largest software development platform.","avatar":"https://github.githubassets.com/images/modules/logos_page/GitHub-Mark.png","label":"links-badge-tech"},{"nick":"定海七中OJ","description":"定海七中在线测评系统","link":"https://dh7zoj.top","avatar":"https://hydro.js.org/favicon.png","label":"links-badge-personal"}],[{"nick":"LaoShui的站点监测","link":"https://status.lao-shui.top","description":"LaoShui的站点监测","avatar":"https://forum.dh7zoj.top/img/laoshui.jpg","label":"links-badge-personal"},{"nick":"New LaoShui's Forum","link":"https://new-forum.dh7zoj.top","description":"LaoShui's Forum","avatar":"https://forum.dh7zoj.top/img/laoshui.jpg","label":"links-badge-personal"}],[{"nick":"LaoShui's Forum","link":"https://forum.dh7zoj.top","description":"之前的LaoShui's Forum","avatar":"https://forum.dh7zoj.top/img/laoshui.jpg","label":"links-badge-personal"},{"nick":"Alist","link":"https://github.com/alist-org/alist","description":"A file list/WebDAV program that supports multiple storages, powered by Gin and Solidjs.","avatar":"https://alist.nn.ci/logo.svg","label":"links-badge-tech"}],[{"nick":"HydroOJ(GitHub)","link":"https://github.com/hydro-dev/Hydro","description":"Hydro - Next generation high performance online-judge platform","avatar":"https://hydro.js.org/favicon.png","label":"links-badge-tech"},{"nick":"HydroOJ","link":"https://hydro.ac","description":"Hydro - Next generation high performance online-judge platform","avatar":"https://hydro.js.org/favicon.png","label":"links-badge-tech"}],[{"nick":"GitHub","link":"https://github.com","description":"GitHub is the world's largest software development platform.","avatar":"https://github.githubassets.com/images/modules/logos_page/GitHub-Mark.png","label":"links-badge-tech"},{"nick":"定海七中OJ","description":"定海七中在线测评系统","link":"https://dh7zoj.top","avatar":"https://hydro.js.org/favicon.png","label":"links-badge-personal"}],[{"nick":"LaoShui的站点监测","link":"https://status.lao-shui.top","description":"LaoShui的站点监测","avatar":"https://forum.dh7zoj.top/img/laoshui.jpg","label":"links-badge-personal"},{"nick":"New LaoShui's Forum","link":"https://new-forum.dh7zoj.top","description":"LaoShui's Forum","avatar":"https://forum.dh7zoj.top/img/laoshui.jpg","label":"links-badge-personal"}],[{"nick":"LaoShui's Forum","link":"https://forum.dh7zoj.top","description":"之前的LaoShui's Forum","avatar":"https://forum.dh7zoj.top/img/laoshui.jpg","label":"links-badge-personal"},{"nick":"Alist","link":"https://github.com/alist-org/alist","description":"A file list/WebDAV program that supports multiple storages, powered by Gin and Solidjs.","avatar":"https://alist.nn.ci/logo.svg","label":"links-badge-tech"}],[{"nick":"HydroOJ(GitHub)","link":"https://github.com/hydro-dev/Hydro","description":"Hydro - Next generation high performance online-judge platform","avatar":"https://hydro.js.org/favicon.png","label":"links-badge-tech"},{"nick":"HydroOJ","link":"https://hydro.ac","description":"Hydro - Next generation high performance online-judge platform","avatar":"https://hydro.js.org/favicon.png","label":"links-badge-tech"}],[{"nick":"GitHub","link":"https://github.com","description":"GitHub is the world's largest software development platform.","avatar":"https://github.githubassets.com/images/modules/logos_page/GitHub-Mark.png","label":"links-badge-tech"},{"nick":"定海七中OJ","description":"定海七中在线测评系统","link":"https://dh7zoj.top","avatar":"https://hydro.js.org/favicon.png","label":"links-badge-personal"}],[{"nick":"LaoShui的站点监测","link":"https://status.lao-shui.top","description":"LaoShui的站点监测","avatar":"https://forum.dh7zoj.top/img/laoshui.jpg","label":"links-badge-personal"},{"nick":"New LaoShui's Forum","link":"https://new-forum.dh7zoj.top","description":"LaoShui's Forum","avatar":"https://forum.dh7zoj.top/img/laoshui.jpg","label":"links-badge-personal"}],[{"nick":"LaoShui's Forum","link":"https://forum.dh7zoj.top","description":"之前的LaoShui's Forum","avatar":"https://forum.dh7zoj.top/img/laoshui.jpg","label":"links-badge-personal"},{"nick":"Alist","link":"https://github.com/alist-org/alist","description":"A file list/WebDAV program that supports multiple storages, powered by Gin and Solidjs.","avatar":"https://alist.nn.ci/logo.svg","label":"links-badge-tech"}],[{"nick":"HydroOJ(GitHub)","link":"https://github.com/hydro-dev/Hydro","description":"Hydro - Next generation high performance online-judge platform","avatar":"https://hydro.js.org/favicon.png","label":"links-badge-tech"},{"nick":"HydroOJ","link":"https://hydro.ac","description":"Hydro - Next generation high performance online-judge platform","avatar":"https://hydro.js.org/favicon.png","label":"links-badge-tech"}],[{"nick":"GitHub","link":"https://github.com","description":"GitHub is the world's largest software development platform.","avatar":"https://github.githubassets.com/images/modules/logos_page/GitHub-Mark.png","label":"links-badge-tech"},{"nick":"定海七中OJ","description":"定海七中在线测评系统","link":"https://dh7zoj.top","avatar":"https://hydro.js.org/favicon.png","label":"links-badge-personal"}],[{"nick":"LaoShui的站点监测","link":"https://status.lao-shui.top","description":"LaoShui的站点监测","avatar":"https://forum.dh7zoj.top/img/laoshui.jpg","label":"links-badge-personal"},{"nick":"New LaoShui's Forum","link":"https://new-forum.dh7zoj.top","description":"LaoShui's Forum","avatar":"https://forum.dh7zoj.top/img/laoshui.jpg","label":"links-badge-personal"}],[{"nick":"LaoShui's Forum","link":"https://forum.dh7zoj.top","description":"之前的LaoShui's Forum","avatar":"https://forum.dh7zoj.top/img/laoshui.jpg","label":"links-badge-personal"},{"nick":"Alist","link":"https://github.com/alist-org/alist","description":"A file list/WebDAV program that supports multiple storages, powered by Gin and Solidjs.","avatar":"https://alist.nn.ci/logo.svg","label":"links-badge-tech"}],[{"nick":"HydroOJ(GitHub)","link":"https://github.com/hydro-dev/Hydro","description":"Hydro - Next generation high performance online-judge platform","avatar":"https://hydro.js.org/favicon.png","label":"links-badge-tech"},{"nick":"HydroOJ","link":"https://hydro.ac","description":"Hydro - Next generation high performance online-judge platform","avatar":"https://hydro.js.org/favicon.png","label":"links-badge-tech"}],[{"nick":"GitHub","link":"https://github.com","description":"GitHub is the world's largest software development platform.","avatar":"https://github.githubassets.com/images/modules/logos_page/GitHub-Mark.png","label":"links-badge-tech"},{"nick":"定海七中OJ","description":"定海七中在线测评系统","link":"https://dh7zoj.top","avatar":"https://hydro.js.org/favicon.png","label":"links-badge-personal"}],[{"nick":"LaoShui的站点监测","link":"https://status.lao-shui.top","description":"LaoShui的站点监测","avatar":"https://forum.dh7zoj.top/img/laoshui.jpg","label":"links-badge-personal"},{"nick":"New LaoShui's Forum","link":"https://new-forum.dh7zoj.top","description":"LaoShui's Forum","avatar":"https://forum.dh7zoj.top/img/laoshui.jpg","label":"links-badge-personal"}],[{"nick":"LaoShui's Forum","link":"https://forum.dh7zoj.top","description":"之前的LaoShui's Forum","avatar":"https://forum.dh7zoj.top/img/laoshui.jpg","label":"links-badge-personal"},{"nick":"Alist","link":"https://github.com/alist-org/alist","description":"A file list/WebDAV program that supports multiple storages, powered by Gin and Solidjs.","avatar":"https://alist.nn.ci/logo.svg","label":"links-badge-tech"}],[{"nick":"HydroOJ(GitHub)","link":"https://github.com/hydro-dev/Hydro","description":"Hydro - Next generation high performance online-judge platform","avatar":"https://hydro.js.org/favicon.png","label":"links-badge-tech"},{"nick":"HydroOJ","link":"https://hydro.ac","description":"Hydro - Next generation high performance online-judge platform","avatar":"https://hydro.js.org/favicon.png","label":"links-badge-tech"}],[{"nick":"GitHub","link":"https://github.com","description":"GitHub is the world's largest software development platform.","avatar":"https://github.githubassets.com/images/modules/logos_page/GitHub-Mark.png","label":"links-badge-tech"},{"nick":"定海七中OJ","description":"定海七中在线测评系统","link":"https://dh7zoj.top","avatar":"https://hydro.js.org/favicon.png","label":"links-badge-personal"}],[{"nick":"LaoShui的站点监测","link":"https://status.lao-shui.top","description":"LaoShui的站点监测","avatar":"https://forum.dh7zoj.top/img/laoshui.jpg","label":"links-badge-personal"},{"nick":"New LaoShui's Forum","link":"https://new-forum.dh7zoj.top","description":"LaoShui's Forum","avatar":"https://forum.dh7zoj.top/img/laoshui.jpg","label":"links-badge-personal"}],[{"nick":"LaoShui's Forum","link":"https://forum.dh7zoj.top","description":"之前的LaoShui's Forum","avatar":"https://forum.dh7zoj.top/img/laoshui.jpg","label":"links-badge-personal"},{"nick":"Alist","link":"https://github.com/alist-org/alist","description":"A file list/WebDAV program that supports multiple storages, powered by Gin and Solidjs.","avatar":"https://alist.nn.ci/logo.svg","label":"links-badge-tech"}],[{"nick":"HydroOJ(GitHub)","link":"https://github.com/hydro-dev/Hydro","description":"Hydro - Next generation high performance online-judge platform","avatar":"https://hydro.js.org/favicon.png","label":"links-badge-tech"},{"nick":"HydroOJ","link":"https://hydro.ac","description":"Hydro - Next generation high performance online-judge platform","avatar":"https://hydro.js.org/favicon.png","label":"links-badge-tech"}],[{"nick":"GitHub","link":"https://github.com","description":"GitHub is the world's largest software development platform.","avatar":"https://github.githubassets.com/images/modules/logos_page/GitHub-Mark.png","label":"links-badge-tech"},{"nick":"定海七中OJ","description":"定海七中在线测评系统","link":"https://dh7zoj.top","avatar":"https://hydro.js.org/favicon.png","label":"links-badge-personal"}],[{"nick":"LaoShui的站点监测","link":"https://status.lao-shui.top","description":"LaoShui的站点监测","avatar":"https://forum.dh7zoj.top/img/laoshui.jpg","label":"links-badge-personal"},{"nick":"New LaoShui's Forum","link":"https://new-forum.dh7zoj.top","description":"LaoShui's Forum","avatar":"https://forum.dh7zoj.top/img/laoshui.jpg","label":"links-badge-personal"}],[{"nick":"LaoShui's Forum","link":"https://forum.dh7zoj.top","description":"之前的LaoShui's Forum","avatar":"https://forum.dh7zoj.top/img/laoshui.jpg","label":"links-badge-personal"},{"nick":"Alist","link":"https://github.com/alist-org/alist","description":"A file list/WebDAV program that supports multiple storages, powered by Gin and Solidjs.","avatar":"https://alist.nn.ci/logo.svg","label":"links-badge-tech"}],[{"nick":"HydroOJ(GitHub)","link":"https://github.com/hydro-dev/Hydro","description":"Hydro - Next generation high performance online-judge platform","avatar":"https://hydro.js.org/favicon.png","label":"links-badge-tech"},{"nick":"HydroOJ","link":"https://hydro.ac","description":"Hydro - Next generation high performance online-judge platform","avatar":"https://hydro.js.org/favicon.png","label":"links-badge-tech"}],[{"nick":"GitHub","link":"https://github.com","description":"GitHub is the world's largest software development platform.","avatar":"https://github.githubassets.com/images/modules/logos_page/GitHub-Mark.png","label":"links-badge-tech"},{"nick":"定海七中OJ","description":"定海七中在线测评系统","link":"https://dh7zoj.top","avatar":"https://hydro.js.org/favicon.png","label":"links-badge-personal"}],[{"nick":"LaoShui的站点监测","link":"https://status.lao-shui.top","description":"LaoShui的站点监测","avatar":"https://forum.dh7zoj.top/img/laoshui.jpg","label":"links-badge-personal"},{"nick":"New LaoShui's Forum","link":"https://new-forum.dh7zoj.top","description":"LaoShui's Forum","avatar":"https://forum.dh7zoj.top/img/laoshui.jpg","label":"links-badge-personal"}],[{"nick":"LaoShui's Forum","link":"https://forum.dh7zoj.top","description":"之前的LaoShui's Forum","avatar":"https://forum.dh7zoj.top/img/laoshui.jpg","label":"links-badge-personal"},{"nick":"Alist","link":"https://github.com/alist-org/alist","description":"A file list/WebDAV program that supports multiple storages, powered by Gin and Solidjs.","avatar":"https://alist.nn.ci/logo.svg","label":"links-badge-tech"}],[{"nick":"HydroOJ(GitHub)","link":"https://github.com/hydro-dev/Hydro","description":"Hydro - Next generation high performance online-judge platform","avatar":"https://hydro.js.org/favicon.png","label":"links-badge-tech"},{"nick":"HydroOJ","link":"https://hydro.ac","description":"Hydro - Next generation high performance online-judge platform","avatar":"https://hydro.js.org/favicon.png","label":"links-badge-tech"}],[{"nick":"GitHub","link":"https://github.com","description":"GitHub is the world's largest software development platform.","avatar":"https://github.githubassets.com/images/modules/logos_page/GitHub-Mark.png","label":"links-badge-tech"},{"nick":"定海七中OJ","description":"定海七中在线测评系统","link":"https://dh7zoj.top","avatar":"https://hydro.js.org/favicon.png","label":"links-badge-personal"}],[{"nick":"LaoShui的站点监测","link":"https://status.lao-shui.top","description":"LaoShui的站点监测","avatar":"https://forum.dh7zoj.top/img/laoshui.jpg","label":"links-badge-personal"},{"nick":"New LaoShui's Forum","link":"https://new-forum.dh7zoj.top","description":"LaoShui's Forum","avatar":"https://forum.dh7zoj.top/img/laoshui.jpg","label":"links-badge-personal"}],[{"nick":"LaoShui's Forum","link":"https://forum.dh7zoj.top","description":"之前的LaoShui's Forum","avatar":"https://forum.dh7zoj.top/img/laoshui.jpg","label":"links-badge-personal"},{"nick":"Alist","link":"https://github.com/alist-org/alist","description":"A file list/WebDAV program that supports multiple storages, powered by Gin and Solidjs.","avatar":"https://alist.nn.ci/logo.svg","label":"links-badge-tech"}],[{"nick":"HydroOJ(GitHub)","link":"https://github.com/hydro-dev/Hydro","description":"Hydro - Next generation high performance online-judge platform","avatar":"https://hydro.js.org/favicon.png","label":"links-badge-tech"},{"nick":"HydroOJ","link":"https://hydro.ac","description":"Hydro - Next generation high performance online-judge platform","avatar":"https://hydro.js.org/favicon.png","label":"links-badge-tech"}]],"data":{"links-badge-tech":[{"nick":"GitHub","link":"https://github.com","description":"GitHub is the world's largest software development platform.","avatar":"https://github.githubassets.com/images/modules/logos_page/GitHub-Mark.png","label":"links-badge-tech"},{"nick":"Alist","link":"https://github.com/alist-org/alist","description":"A file list/WebDAV program that supports multiple storages, powered by Gin and Solidjs.","avatar":"https://alist.nn.ci/logo.svg","label":"links-badge-tech"},{"nick":"HydroOJ(GitHub)","link":"https://github.com/hydro-dev/Hydro","description":"Hydro - Next generation high performance online-judge platform","avatar":"https://hydro.js.org/favicon.png","label":"links-badge-tech"},{"nick":"HydroOJ","link":"https://hydro.ac","description":"Hydro - Next generation high performance online-judge platform","avatar":"https://hydro.js.org/favicon.png","label":"links-badge-tech"}],"links-badge-personal":[{"nick":"定海七中OJ","description":"定海七中在线测评系统","link":"https://dh7zoj.top","avatar":"https://hydro.js.org/favicon.png","label":"links-badge-personal"},{"nick":"LaoShui的站点监测","link":"https://status.lao-shui.top","description":"LaoShui的站点监测","avatar":"https://forum.dh7zoj.top/img/laoshui.jpg","label":"links-badge-personal"},{"nick":"New LaoShui's Forum","link":"https://new-forum.dh7zoj.top","description":"LaoShui's Forum","avatar":"https://forum.dh7zoj.top/img/laoshui.jpg","label":"links-badge-personal"},{"nick":"LaoShui's Forum","link":"https://forum.dh7zoj.top","description":"之前的LaoShui's Forum","avatar":"https://forum.dh7zoj.top/img/laoshui.jpg","label":"links-badge-personal"}]}}